MANIFEST.in
README.txt
setup.cfg
setup.py
Products/__init__.py
Products.openstudy.egg-info/PKG-INFO
Products.openstudy.egg-info/SOURCES.txt
Products.openstudy.egg-info/dependency_links.txt
Products.openstudy.egg-info/entry_points.txt
Products.openstudy.egg-info/namespace_packages.txt
Products.openstudy.egg-info/not-zip-safe
Products.openstudy.egg-info/requires.txt
Products.openstudy.egg-info/top_level.txt
Products/openstudy/__init__.py
Products/openstudy/configure.zcml
Products/openstudy/tests.py
Products/openstudy/version.txt
Products/openstudy/browser/__init__.py
Products/openstudy/browser/configure.zcml
Products/openstudy/browser/controlpanel.py
Products/openstudy/browser/studygroup.py
Products/openstudy/portlets/__init__.py
Products/openstudy/portlets/configure.zcml
Products/openstudy/portlets/openstudy.py
Products/openstudy/portlets/openstudyportlet.pt
Products/openstudy/profiles/default/actions.xml
Products/openstudy/profiles/default/controlpanel.xml
Products/openstudy/profiles/default/metadata.xml
Products/openstudy/profiles/default/portlets.xml
Products/openstudy/profiles/default/propertiestool.xml
docs/HISTORY.txt
docs/INSTALL.txt
docs/LICENSE.GPL
docs/LICENSE.txt