Metadata-Version: 1.0
Name: Products.openstudy
Version: 1.1
Summary: Integrating Plone with OpenStudy.
Home-page: http://svn.plone.org/svn/collective/
Author: Brent Lambert
Author-email: brent@enpraxis.net
License: GPL
Keywords: education study studygroup
Platform: UNKNOWN
Classifier: Framework :: Plone
Classifier: Programming Language :: Python
Classifier: License :: OSI Approved :: GNU General Public License (GPL)
